worth_calculator_mcp.py
worth_calculator_mcp/__init__.py
worth_calculator_mcp/main.py
worth_calculator_mcp-0.1.0.dist-info/METADATA
worth_calculator_mcp-0.1.0.dist-info/WHEEL
worth_calculator_mcp-0.1.0.dist-info/entry_points.txt
worth_calculator_mcp-0.1.0.dist-info/top_level.txt
worth_calculator_mcp-0.1.0.dist-info/RECORD
